LICENSE
README.md
setup.cfg
setup.py
kadenapy/__init__.py
kadenapy/url.py
kadenapy.egg-info/PKG-INFO
kadenapy.egg-info/SOURCES.txt
kadenapy.egg-info/dependency_links.txt
kadenapy.egg-info/requires.txt
kadenapy.egg-info/top_level.txt